hellpy/__init__.py
hellpy/exceptions.py
hellpy/requests.py
hellpy/store.py
hellpy/tokens.py
hellpy/utils.py
hellpy/structures/__init__.py
hellpy/structures/builders.py
hellpy/structures/response.py
hellpy/structures/statements.py
hellpy/structures/types.py
hellpy-1.1.0.dist-info/LICENSE
hellpy-1.1.0.dist-info/METADATA
hellpy-1.1.0.dist-info/WHEEL
hellpy-1.1.0.dist-info/top_level.txt
hellpy-1.1.0.dist-info/RECORD
