Metadata-Version: 2.1
Name: hellpy
Version: 1.1.0
Summary: A connector for HellDB.
Home-page: https://github.com/helldatabase/hellpy
Author: Manan (mentix02)
Author-email: manan.yadav02@gmail.com
License: MIT
Platform: UNKNOWN
Classifier: Topic :: Database
Classifier: Topic :: Internet
Classifier: Topic :: Internet :: WWW/HTTP
Classifier: Operating System :: OS Independent
Classifier: Programming Language :: Python :: 3
Classifier: Programming Language :: Python :: 3.7
Classifier: Programming Language :: Python :: 3.8
Classifier: License :: OSI Approved :: MIT License
Requires-Python: >=3.6
